{
  "type": "FeatureCollection",
  "features": [
    {
      "type": "Feature",
      "geometry": { "type": "Point", "coordinates": [103.8298, 1.2494] },
      "properties": { "id": "sentosa", "name": "Sentosa Island", "price": 120, "group": "Light Blue", "type": "property", "index": 0 }
    },
    {
      "type": "Feature",
      "geometry": { "type": "Point", "coordinates": [103.8438, 1.2848] },
      "properties": { "id": "chinatown", "name": "Chinatown", "price": 180, "group": "Orange", "type": "property", "index": 1 }
    },
    {
      "type": "Feature",
      "geometry": { "type": "Point", "coordinates": [103.8443, 1.2905] },
      "properties": { "id": "clarke", "name": "Clarke Quay", "price": 140, "group": "Pink", "type": "property", "index": 2 }
    },
    {
      "type": "Feature",
      "geometry": { "type": "Point", "coordinates": [103.8610, 1.2920] },
      "properties": { "id": "car", "name": "F1 Pit Building (Car)", "price": 250, "group": "Vehicle", "type": "vehicle", "index": 3 }
    },
    {
      "type": "Feature",
      "geometry": { "type": "Point", "coordinates": [103.8523, 1.2830] },
      "properties": { "id": "raffles", "name": "Raffles Place", "price": 320, "group": "Green", "type": "property", "index": 4 }
    },
    {
      "type": "Feature",
      "geometry": { "type": "Point", "coordinates": [103.8545, 1.2868] },
      "properties": { "id": "merlion", "name": "Merlion Park", "price": 300, "group": "Green", "type": "property", "index": 5 }
    },
    {
      "type": "Feature",
      "geometry": { "type": "Point", "coordinates": [103.8643, 1.2816] },
      "properties": { "id": "gbtb", "name": "Gardens by the Bay", "price": 350, "group": "Dark Blue", "type": "property", "index": 6 }
    },
    {
      "type": "Feature",
      "geometry": { "type": "Point", "coordinates": [103.8590, 1.2834] },
      "properties": { "id": "mbs", "name": "Marina Bay Sands", "price": 400, "group": "Dark Blue", "type": "property", "index": 7 }
    },
    {
      "type": "Feature",
      "geometry": { "type": "Point", "coordinates": [103.8680, 1.2720] },
      "properties": { "id": "heli", "name": "Marina South (Helicopter)", "price": 350, "group": "Vehicle", "type": "vehicle", "index": 8 }
    },
    {
      "type": "Feature",
      "geometry": { "type": "Point", "coordinates": [103.8558, 1.3008] },
      "properties": { "id": "bugis", "name": "Bugis", "price": 260, "group": "Yellow", "type": "property", "index": 9 }
    },
    {
      "type": "Feature",
      "geometry": { "type": "Point", "coordinates": [103.8501, 1.3068] },
      "properties": { "id": "littleindia", "name": "Little India", "price": 200, "group": "Orange", "type": "property", "index": 10 }
    },
    {
      "type": "Feature",
      "geometry": { "type": "Point", "coordinates": [103.8318, 1.3038] },
      "properties": { "id": "orchard", "name": "Orchard Road", "price": 280, "group": "Red", "type": "property", "index": 11 }
    },
    {
      "type": "Feature",
      "geometry": { "type": "Point", "coordinates": [103.7406, 1.3328] },
      "properties": { "id": "jurong", "name": "Jurong East MRT", "price": 200, "group": "Station", "type": "station", "index": 12 }
    },
    {
      "type": "Feature",
      "geometry": { "type": "Point", "coordinates": [103.8670, 1.4160] },
      "properties": { "id": "aircraft", "name": "Seletar Airport (Aircraft)", "price": 450, "group": "Vehicle", "type": "vehicle", "index": 13 }
    },
    {
      "type": "Feature",
      "geometry": { "type": "Point", "coordinates": [103.9893, 1.3601] },
      "properties": { "id": "changi", "name": "Changi Airport", "price": 200, "group": "Station", "type": "station", "index": 14 }
    },
    {
      "type": "Feature",
      "geometry": { "type": "Point", "coordinates": [103.7930, 1.4040] },
      "properties": { "id": "zoo", "name": "Singapore Zoo", "price": 300, "group": "Yellow", "type": "property", "index": 15 }
    },
    {
      "type": "Feature",
      "geometry": { "type": "Point", "coordinates": [103.8180, 1.2580] },
      "properties": { "id": "oceanarium", "name": "S.E.A. Aquarium", "price": 250, "group": "Light Blue", "type": "property", "index": 16 }
    },
    {
      "type": "Feature",
      "geometry": { "type": "Point", "coordinates": [103.7650, 1.2720] },
      "properties": { "id": "port", "name": "PSA Container Port", "price": 200, "group": "Station", "type": "station", "index": 17 }
    }
  ]
}